{"errors":[],"warnings":[],"namedChunkGroups":{"app":{"chunks":[10,0,9,4],"assets":["webpack-runtime-68284010de78b5306ed1.js","webpack-runtime-68284010de78b5306ed1.js.map","styles.e887f572731845bb9c95.css","styles-9b6f388623a2ec93d35f.js","styles-9b6f388623a2ec93d35f.js.map","framework-20335242239071f73386.js","framework-20335242239071f73386.js.map","app-e60190cf402ecbbd4e38.js","app-e60190cf402ecbbd4e38.js.map"],"children":{},"childAssets":{}},"component---src-pages-404-js":{"chunks":[0,2,1,3,5],"assets":["styles.e887f572731845bb9c95.css","styles-9b6f388623a2ec93d35f.js","styles-9b6f388623a2ec93d35f.js.map","cb1608f2-1f2daa7a50f50b43f3ba.js","cb1608f2-1f2daa7a50f50b43f3ba.js.map","a9a7754c-9b5ed03f92075f68d3b8.js","a9a7754c-9b5ed03f92075f68d3b8.js.map","commons-aad3336cef5fbb8bc949.js","commons-aad3336cef5fbb8bc949.js.map","component---src-pages-404-js-b5ccc538021028b7aece.js","component---src-pages-404-js-b5ccc538021028b7aece.js.map"],"children":{},"childAssets":{}},"component---src-templates-blog-post-js":{"chunks":[0,2,1,3,6],"assets":["styles.e887f572731845bb9c95.css","styles-9b6f388623a2ec93d35f.js","styles-9b6f388623a2ec93d35f.js.map","cb1608f2-1f2daa7a50f50b43f3ba.js","cb1608f2-1f2daa7a50f50b43f3ba.js.map","a9a7754c-9b5ed03f92075f68d3b8.js","a9a7754c-9b5ed03f92075f68d3b8.js.map","commons-aad3336cef5fbb8bc949.js","commons-aad3336cef5fbb8bc949.js.map","component---src-templates-blog-post-js-506efcdc96821acbb4ef.js","component---src-templates-blog-post-js-506efcdc96821acbb4ef.js.map"],"children":{},"childAssets":{}},"component---src-templates-index-js":{"chunks":[0,2,1,3,7],"assets":["styles.e887f572731845bb9c95.css","styles-9b6f388623a2ec93d35f.js","styles-9b6f388623a2ec93d35f.js.map","cb1608f2-1f2daa7a50f50b43f3ba.js","cb1608f2-1f2daa7a50f50b43f3ba.js.map","a9a7754c-9b5ed03f92075f68d3b8.js","a9a7754c-9b5ed03f92075f68d3b8.js.map","commons-aad3336cef5fbb8bc949.js","commons-aad3336cef5fbb8bc949.js.map","component---src-templates-index-js-8321629be33b874ce7c0.js","component---src-templates-index-js-8321629be33b874ce7c0.js.map"],"children":{},"childAssets":{}},"component---src-templates-tag-js":{"chunks":[0,2,1,3,8],"assets":["styles.e887f572731845bb9c95.css","styles-9b6f388623a2ec93d35f.js","styles-9b6f388623a2ec93d35f.js.map","cb1608f2-1f2daa7a50f50b43f3ba.js","cb1608f2-1f2daa7a50f50b43f3ba.js.map","a9a7754c-9b5ed03f92075f68d3b8.js","a9a7754c-9b5ed03f92075f68d3b8.js.map","commons-aad3336cef5fbb8bc949.js","commons-aad3336cef5fbb8bc949.js.map","component---src-templates-tag-js-119352124b9bb415dac4.js","component---src-templates-tag-js-119352124b9bb415dac4.js.map"],"children":{},"childAssets":{}}},"assetsByChunkName":{"app":["webpack-runtime-68284010de78b5306ed1.js","styles.e887f572731845bb9c95.css","styles-9b6f388623a2ec93d35f.js","framework-20335242239071f73386.js","app-e60190cf402ecbbd4e38.js"],"component---src-pages-404-js":["styles.e887f572731845bb9c95.css","styles-9b6f388623a2ec93d35f.js","cb1608f2-1f2daa7a50f50b43f3ba.js","a9a7754c-9b5ed03f92075f68d3b8.js","commons-aad3336cef5fbb8bc949.js","component---src-pages-404-js-b5ccc538021028b7aece.js"],"component---src-templates-blog-post-js":["styles.e887f572731845bb9c95.css","styles-9b6f388623a2ec93d35f.js","cb1608f2-1f2daa7a50f50b43f3ba.js","a9a7754c-9b5ed03f92075f68d3b8.js","commons-aad3336cef5fbb8bc949.js","component---src-templates-blog-post-js-506efcdc96821acbb4ef.js"],"component---src-templates-index-js":["styles.e887f572731845bb9c95.css","styles-9b6f388623a2ec93d35f.js","cb1608f2-1f2daa7a50f50b43f3ba.js","a9a7754c-9b5ed03f92075f68d3b8.js","commons-aad3336cef5fbb8bc949.js","component---src-templates-index-js-8321629be33b874ce7c0.js"],"component---src-templates-tag-js":["styles.e887f572731845bb9c95.css","styles-9b6f388623a2ec93d35f.js","cb1608f2-1f2daa7a50f50b43f3ba.js","a9a7754c-9b5ed03f92075f68d3b8.js","commons-aad3336cef5fbb8bc949.js","component---src-templates-tag-js-119352124b9bb415dac4.js"]}}